{
    "dataset": "cifar10",
    "clustering_method": "kmeans",
    "repr_method": "max",
    "partition_method": "square",
    "num_partitions": 2,
    "k": 352,
    "sub_k": 512,
    "nnac": {
        "2": 0,
        "509": 0,
        "7": 1,
        "350": 1,
        "68": 2,
        "225": 2,
        "8": 2,
        "267": 2,
        "269": 2,
        "183": 2,
        "344": 2,
        "317": 2,
        "231": 3,
        "288": 3,
        "11": 3,
        "146": 3,
        "116": 3,
        "316": 3,
        "12": 4,
        "57": 4,
        "133": 5,
        "382": 5,
        "394": 5,
        "13": 5,
        "14": 5,
        "277": 5,
        "21": 5,
        "409": 5,
        "25": 5,
        "282": 5,
        "413": 5,
        "415": 5,
        "293": 5,
        "39": 5,
        "299": 5,
        "428": 5,
        "306": 5,
        "437": 5,
        "54": 5,
        "438": 5,
        "314": 5,
        "195": 5,
        "324": 5,
        "325": 5,
        "198": 5,
        "71": 5,
        "201": 5,
        "458": 5,
        "332": 5,
        "460": 5,
        "206": 5,
        "79": 5,
        "81": 5,
        "82": 5,
        "89": 5,
        "222": 5,
        "96": 5,
        "226": 5,
        "486": 5,
        "102": 5,
        "490": 5,
        "372": 5,
        "245": 5,
        "124": 5,
        "510": 5,
        "16": 6,
        "109": 6,
        "20": 7,
        "379": 7,
        "92": 8,
        "161": 8,
        "327": 8,
        "23": 8,
        "435": 9,
        "449": 9,
        "51": 9,
        "150": 9,
        "24": 9,
        "284": 9,
        "159": 9,
        "26": 10,
        "408": 10,
        "493": 10,
        "28": 11,
        "436": 11,
        "30": 12,
        "90": 12,
        "260": 13,
        "390": 13,
        "138": 13,
        "397": 13,
        "143": 13,
        "281": 13,
        "33": 13,
        "291": 13,
        "420": 13,
        "56": 13,
        "447": 13,
        "322": 13,
        "70": 13,
        "205": 13,
        "348": 13,
        "93": 13,
        "478": 13,
        "99": 13,
        "108": 13,
        "367": 13,
        "240": 13,
        "368": 13,
        "35": 14,
        "140": 14,
        "37": 15,
        "433": 15,
        "178": 15,
        "407": 15,
        "506": 15,
        "220": 15,
        "45": 16,
        "217": 16,
        "439": 16,
        "67": 17,
        "385": 17,
        "104": 17,
        "429": 17,
        "212": 17,
        "309": 17,
        "502": 17,
        "258": 18,
        "448": 18,
        "75": 18,
        "88": 19,
        "227": 19,
        "91": 20,
        "234": 20,
        "237": 21,
        "330": 21,
        "209": 21,
        "498": 21,
        "181": 21,
        "343": 21,
        "95": 21,
        "118": 22,
        "491": 22,
        "119": 23,
        "257": 23,
        "132": 24,
        "214": 24,
        "134": 25,
        "221": 25,
        "137": 26,
        "165": 26,
        "147": 27,
        "364": 27,
        "259": 28,
        "384": 28,
        "393": 28,
        "395": 28,
        "278": 28,
        "154": 28,
        "416": 28,
        "289": 28,
        "418": 28,
        "419": 28,
        "294": 28,
        "434": 28,
        "310": 28,
        "311": 28,
        "464": 28,
        "469": 28,
        "476": 28,
        "361": 28,
        "494": 28,
        "500": 28,
        "248": 28,
        "157": 29,
        "249": 29,
        "405": 29,
        "166": 30,
        "359": 30,
        "179": 31,
        "208": 31,
        "188": 32,
        "487": 32,
        "189": 33,
        "414": 33,
        "223": 34,
        "263": 34,
        "241": 35,
        "265": 35,
        "292": 36,
        "442": 36,
        "323": 37,
        "427": 37,
        "362": 38,
        "484": 38,
        "402": 38,
        "377": 39,
        "403": 39,
        "375": 39,
        "406": 40,
        "508": 40,
        "0": 41,
        "1": 42,
        "3": 43,
        "4": 44,
        "5": 45,
        "6": 46,
        "9": 47,
        "10": 48,
        "15": 49,
        "17": 50,
        "18": 51,
        "19": 52,
        "22": 53,
        "27": 54,
        "29": 55,
        "31": 56,
        "32": 57,
        "34": 58,
        "36": 59,
        "38": 60,
        "40": 61,
        "41": 62,
        "42": 63,
        "43": 64,
        "44": 65,
        "46": 66,
        "47": 67,
        "48": 68,
        "49": 69,
        "50": 70,
        "52": 71,
        "53": 72,
        "55": 73,
        "58": 74,
        "59": 75,
        "60": 76,
        "61": 77,
        "62": 78,
        "63": 79,
        "64": 80,
        "65": 81,
        "66": 82,
        "69": 83,
        "72": 84,
        "73": 85,
        "74": 86,
        "76": 87,
        "77": 88,
        "78": 89,
        "80": 90,
        "83": 91,
        "84": 92,
        "85": 93,
        "86": 94,
        "87": 95,
        "94": 96,
        "97": 97,
        "98": 98,
        "100": 99,
        "101": 100,
        "103": 101,
        "105": 102,
        "106": 103,
        "107": 104,
        "110": 105,
        "111": 106,
        "112": 107,
        "113": 108,
        "114": 109,
        "115": 110,
        "117": 111,
        "120": 112,
        "121": 113,
        "122": 114,
        "123": 115,
        "125": 116,
        "126": 117,
        "127": 118,
        "128": 119,
        "129": 120,
        "130": 121,
        "131": 122,
        "135": 123,
        "136": 124,
        "139": 125,
        "141": 126,
        "142": 127,
        "144": 128,
        "145": 129,
        "148": 130,
        "149": 131,
        "151": 132,
        "152": 133,
        "153": 134,
        "155": 135,
        "156": 136,
        "158": 137,
        "160": 138,
        "162": 139,
        "163": 140,
        "164": 141,
        "167": 142,
        "168": 143,
        "169": 144,
        "170": 145,
        "171": 146,
        "172": 147,
        "173": 148,
        "174": 149,
        "175": 150,
        "176": 151,
        "177": 152,
        "180": 153,
        "182": 154,
        "184": 155,
        "185": 156,
        "186": 157,
        "187": 158,
        "190": 159,
        "191": 160,
        "192": 161,
        "193": 162,
        "194": 163,
        "196": 164,
        "197": 165,
        "199": 166,
        "200": 167,
        "202": 168,
        "203": 169,
        "204": 170,
        "207": 171,
        "210": 172,
        "211": 173,
        "213": 174,
        "215": 175,
        "216": 176,
        "218": 177,
        "219": 178,
        "224": 179,
        "228": 180,
        "229": 181,
        "230": 182,
        "232": 183,
        "233": 184,
        "235": 185,
        "236": 186,
        "238": 187,
        "239": 188,
        "242": 189,
        "243": 190,
        "244": 191,
        "246": 192,
        "247": 193,
        "250": 194,
        "251": 195,
        "252": 196,
        "253": 197,
        "254": 198,
        "255": 199,
        "256": 200,
        "261": 201,
        "262": 202,
        "264": 203,
        "266": 204,
        "268": 205,
        "270": 206,
        "271": 207,
        "272": 208,
        "273": 209,
        "274": 210,
        "275": 211,
        "276": 212,
        "279": 213,
        "280": 214,
        "283": 215,
        "285": 216,
        "286": 217,
        "287": 218,
        "290": 219,
        "295": 220,
        "296": 221,
        "297": 222,
        "298": 223,
        "300": 224,
        "301": 225,
        "302": 226,
        "303": 227,
        "304": 228,
        "305": 229,
        "307": 230,
        "308": 231,
        "312": 232,
        "313": 233,
        "315": 234,
        "318": 235,
        "319": 236,
        "320": 237,
        "321": 238,
        "326": 239,
        "328": 240,
        "329": 241,
        "331": 242,
        "333": 243,
        "334": 244,
        "335": 245,
        "336": 246,
        "337": 247,
        "338": 248,
        "339": 249,
        "340": 250,
        "341": 251,
        "342": 252,
        "345": 253,
        "346": 254,
        "347": 255,
        "349": 256,
        "351": 257,
        "352": 258,
        "353": 259,
        "354": 260,
        "355": 261,
        "356": 262,
        "357": 263,
        "358": 264,
        "360": 265,
        "363": 266,
        "365": 267,
        "366": 268,
        "369": 269,
        "370": 270,
        "371": 271,
        "373": 272,
        "374": 273,
        "376": 274,
        "378": 275,
        "380": 276,
        "381": 277,
        "383": 278,
        "386": 279,
        "387": 280,
        "388": 281,
        "389": 282,
        "391": 283,
        "392": 284,
        "396": 285,
        "398": 286,
        "399": 287,
        "400": 288,
        "401": 289,
        "404": 290,
        "410": 291,
        "411": 292,
        "412": 293,
        "417": 294,
        "421": 295,
        "422": 296,
        "423": 297,
        "424": 298,
        "425": 299,
        "426": 300,
        "430": 301,
        "431": 302,
        "432": 303,
        "440": 304,
        "441": 305,
        "443": 306,
        "444": 307,
        "445": 308,
        "446": 309,
        "450": 310,
        "451": 311,
        "452": 312,
        "453": 313,
        "454": 314,
        "455": 315,
        "456": 316,
        "457": 317,
        "459": 318,
        "461": 319,
        "462": 320,
        "463": 321,
        "465": 322,
        "466": 323,
        "467": 324,
        "468": 325,
        "470": 326,
        "471": 327,
        "472": 328,
        "473": 329,
        "474": 330,
        "475": 331,
        "477": 332,
        "479": 333,
        "480": 334,
        "481": 335,
        "482": 336,
        "483": 337,
        "485": 338,
        "488": 339,
        "489": 340,
        "492": 341,
        "495": 342,
        "496": 343,
        "497": 344,
        "499": 345,
        "501": 346,
        "503": 347,
        "504": 348,
        "505": 349,
        "507": 350,
        "511": 351
    }
}