{
    "dataset": "cifar100",
    "clustering_method": "kmeans",
    "repr_method": "max",
    "partition_method": "square",
    "num_partitions": 2,
    "k": 352,
    "sub_k": 512,
    "nnac": {
        "39": 0,
        "192": 0,
        "176": 1,
        "205": 1,
        "252": 1,
        "418": 1,
        "445": 1,
        "111": 2,
        "235": 2,
        "389": 2,
        "14": 3,
        "36": 3,
        "40": 3,
        "79": 3,
        "187": 3,
        "188": 3,
        "262": 3,
        "288": 3,
        "290": 3,
        "345": 3,
        "364": 3,
        "372": 3,
        "377": 3,
        "404": 3,
        "406": 3,
        "438": 3,
        "453": 3,
        "510": 3,
        "87": 4,
        "110": 4,
        "429": 4,
        "3": 5,
        "4": 5,
        "8": 5,
        "13": 5,
        "24": 5,
        "25": 5,
        "27": 5,
        "46": 5,
        "48": 5,
        "53": 5,
        "62": 5,
        "66": 5,
        "92": 5,
        "100": 5,
        "103": 5,
        "109": 5,
        "115": 5,
        "117": 5,
        "120": 5,
        "123": 5,
        "127": 5,
        "131": 5,
        "132": 5,
        "145": 5,
        "158": 5,
        "163": 5,
        "165": 5,
        "167": 5,
        "168": 5,
        "172": 5,
        "174": 5,
        "182": 5,
        "183": 5,
        "191": 5,
        "198": 5,
        "201": 5,
        "211": 5,
        "232": 5,
        "243": 5,
        "246": 5,
        "251": 5,
        "255": 5,
        "260": 5,
        "273": 5,
        "297": 5,
        "302": 5,
        "303": 5,
        "306": 5,
        "317": 5,
        "327": 5,
        "331": 5,
        "335": 5,
        "344": 5,
        "366": 5,
        "370": 5,
        "380": 5,
        "386": 5,
        "387": 5,
        "392": 5,
        "405": 5,
        "412": 5,
        "413": 5,
        "417": 5,
        "420": 5,
        "441": 5,
        "444": 5,
        "448": 5,
        "458": 5,
        "462": 5,
        "468": 5,
        "474": 5,
        "480": 5,
        "483": 5,
        "497": 5,
        "502": 5,
        "503": 5,
        "34": 6,
        "488": 6,
        "54": 7,
        "76": 7,
        "209": 7,
        "0": 8,
        "15": 8,
        "43": 8,
        "65": 8,
        "75": 8,
        "85": 8,
        "124": 8,
        "144": 8,
        "146": 8,
        "169": 8,
        "171": 8,
        "195": 8,
        "214": 8,
        "218": 8,
        "271": 8,
        "276": 8,
        "293": 8,
        "356": 8,
        "359": 8,
        "373": 8,
        "481": 8,
        "487": 8,
        "19": 9,
        "67": 9,
        "69": 9,
        "227": 9,
        "320": 9,
        "500": 9,
        "12": 10,
        "49": 10,
        "154": 10,
        "200": 10,
        "368": 10,
        "363": 11,
        "369": 11,
        "399": 11,
        "21": 12,
        "396": 12,
        "128": 13,
        "245": 13,
        "23": 14,
        "74": 14,
        "180": 15,
        "222": 15,
        "248": 16,
        "434": 16,
        "230": 17,
        "475": 17,
        "280": 18,
        "294": 18,
        "324": 19,
        "337": 19,
        "105": 20,
        "122": 20,
        "139": 20,
        "10": 21,
        "29": 21,
        "41": 21,
        "90": 21,
        "478": 21,
        "102": 22,
        "272": 22,
        "343": 22,
        "508": 22,
        "257": 23,
        "465": 23,
        "148": 24,
        "226": 24,
        "1": 25,
        "219": 25,
        "58": 26,
        "177": 26,
        "258": 26,
        "231": 27,
        "253": 27,
        "55": 28,
        "162": 28,
        "511": 29,
        "509": 30,
        "507": 31,
        "506": 32,
        "505": 33,
        "504": 34,
        "501": 35,
        "499": 36,
        "498": 37,
        "496": 38,
        "495": 39,
        "494": 40,
        "493": 41,
        "492": 42,
        "491": 43,
        "490": 44,
        "489": 45,
        "486": 46,
        "485": 47,
        "484": 48,
        "482": 49,
        "479": 50,
        "477": 51,
        "476": 52,
        "473": 53,
        "472": 54,
        "471": 55,
        "470": 56,
        "469": 57,
        "467": 58,
        "466": 59,
        "464": 60,
        "463": 61,
        "461": 62,
        "460": 63,
        "459": 64,
        "457": 65,
        "456": 66,
        "455": 67,
        "454": 68,
        "452": 69,
        "451": 70,
        "450": 71,
        "449": 72,
        "447": 73,
        "446": 74,
        "443": 75,
        "442": 76,
        "440": 77,
        "439": 78,
        "437": 79,
        "436": 80,
        "435": 81,
        "433": 82,
        "432": 83,
        "431": 84,
        "430": 85,
        "428": 86,
        "427": 87,
        "426": 88,
        "425": 89,
        "424": 90,
        "423": 91,
        "422": 92,
        "421": 93,
        "419": 94,
        "416": 95,
        "415": 96,
        "414": 97,
        "411": 98,
        "410": 99,
        "409": 100,
        "408": 101,
        "407": 102,
        "403": 103,
        "402": 104,
        "401": 105,
        "400": 106,
        "398": 107,
        "397": 108,
        "395": 109,
        "394": 110,
        "393": 111,
        "391": 112,
        "390": 113,
        "388": 114,
        "385": 115,
        "384": 116,
        "383": 117,
        "382": 118,
        "381": 119,
        "379": 120,
        "378": 121,
        "376": 122,
        "375": 123,
        "374": 124,
        "371": 125,
        "367": 126,
        "365": 127,
        "362": 128,
        "361": 129,
        "360": 130,
        "358": 131,
        "357": 132,
        "355": 133,
        "354": 134,
        "353": 135,
        "352": 136,
        "351": 137,
        "350": 138,
        "349": 139,
        "348": 140,
        "347": 141,
        "346": 142,
        "342": 143,
        "341": 144,
        "340": 145,
        "339": 146,
        "338": 147,
        "336": 148,
        "334": 149,
        "333": 150,
        "332": 151,
        "330": 152,
        "329": 153,
        "328": 154,
        "326": 155,
        "325": 156,
        "323": 157,
        "322": 158,
        "321": 159,
        "319": 160,
        "318": 161,
        "316": 162,
        "315": 163,
        "314": 164,
        "313": 165,
        "312": 166,
        "311": 167,
        "310": 168,
        "309": 169,
        "308": 170,
        "307": 171,
        "305": 172,
        "304": 173,
        "301": 174,
        "300": 175,
        "299": 176,
        "298": 177,
        "296": 178,
        "295": 179,
        "292": 180,
        "291": 181,
        "289": 182,
        "287": 183,
        "286": 184,
        "285": 185,
        "284": 186,
        "283": 187,
        "282": 188,
        "281": 189,
        "279": 190,
        "278": 191,
        "277": 192,
        "275": 193,
        "274": 194,
        "270": 195,
        "269": 196,
        "268": 197,
        "267": 198,
        "266": 199,
        "265": 200,
        "264": 201,
        "263": 202,
        "261": 203,
        "259": 204,
        "256": 205,
        "254": 206,
        "250": 207,
        "249": 208,
        "247": 209,
        "244": 210,
        "242": 211,
        "241": 212,
        "240": 213,
        "239": 214,
        "238": 215,
        "237": 216,
        "236": 217,
        "234": 218,
        "233": 219,
        "229": 220,
        "228": 221,
        "225": 222,
        "224": 223,
        "223": 224,
        "221": 225,
        "220": 226,
        "217": 227,
        "216": 228,
        "215": 229,
        "213": 230,
        "212": 231,
        "210": 232,
        "208": 233,
        "207": 234,
        "206": 235,
        "204": 236,
        "203": 237,
        "202": 238,
        "199": 239,
        "197": 240,
        "196": 241,
        "194": 242,
        "193": 243,
        "190": 244,
        "189": 245,
        "186": 246,
        "185": 247,
        "184": 248,
        "181": 249,
        "179": 250,
        "178": 251,
        "175": 252,
        "173": 253,
        "170": 254,
        "166": 255,
        "164": 256,
        "161": 257,
        "160": 258,
        "159": 259,
        "157": 260,
        "156": 261,
        "155": 262,
        "153": 263,
        "152": 264,
        "151": 265,
        "150": 266,
        "149": 267,
        "147": 268,
        "143": 269,
        "142": 270,
        "141": 271,
        "140": 272,
        "138": 273,
        "137": 274,
        "136": 275,
        "135": 276,
        "134": 277,
        "133": 278,
        "130": 279,
        "129": 280,
        "126": 281,
        "125": 282,
        "121": 283,
        "119": 284,
        "118": 285,
        "116": 286,
        "114": 287,
        "113": 288,
        "112": 289,
        "108": 290,
        "107": 291,
        "106": 292,
        "104": 293,
        "101": 294,
        "99": 295,
        "98": 296,
        "97": 297,
        "96": 298,
        "95": 299,
        "94": 300,
        "93": 301,
        "91": 302,
        "89": 303,
        "88": 304,
        "86": 305,
        "84": 306,
        "83": 307,
        "82": 308,
        "81": 309,
        "80": 310,
        "78": 311,
        "77": 312,
        "73": 313,
        "72": 314,
        "71": 315,
        "70": 316,
        "68": 317,
        "64": 318,
        "63": 319,
        "61": 320,
        "60": 321,
        "59": 322,
        "57": 323,
        "56": 324,
        "52": 325,
        "51": 326,
        "50": 327,
        "47": 328,
        "45": 329,
        "44": 330,
        "42": 331,
        "38": 332,
        "37": 333,
        "35": 334,
        "33": 335,
        "32": 336,
        "31": 337,
        "30": 338,
        "28": 339,
        "26": 340,
        "22": 341,
        "20": 342,
        "18": 343,
        "17": 344,
        "16": 345,
        "11": 346,
        "9": 347,
        "7": 348,
        "6": 349,
        "5": 350,
        "2": 351
    }
}