{
    "dataset": "svhn",
    "clustering_method": "kmeans",
    "repr_method": "max",
    "partition_method": "square",
    "num_partitions": 2,
    "k": 896,
    "sub_k": 1024,
    "nnac": {
        "18": 0,
        "82": 0,
        "171": 0,
        "186": 0,
        "233": 0,
        "423": 0,
        "487": 0,
        "498": 0,
        "500": 0,
        "520": 0,
        "656": 0,
        "794": 0,
        "892": 0,
        "964": 0,
        "995": 0,
        "1001": 0,
        "1003": 0,
        "216": 1,
        "581": 1,
        "7": 2,
        "10": 2,
        "111": 2,
        "261": 2,
        "294": 2,
        "415": 2,
        "435": 2,
        "461": 2,
        "531": 2,
        "534": 2,
        "611": 2,
        "779": 2,
        "916": 2,
        "963": 2,
        "999": 2,
        "1006": 2,
        "243": 3,
        "389": 3,
        "440": 3,
        "564": 4,
        "793": 4,
        "93": 5,
        "490": 5,
        "245": 6,
        "868": 6,
        "42": 7,
        "330": 7,
        "783": 7,
        "25": 8,
        "488": 8,
        "984": 8,
        "346": 9,
        "833": 9,
        "181": 10,
        "370": 10,
        "159": 11,
        "246": 11,
        "437": 11,
        "734": 12,
        "847": 12,
        "201": 13,
        "237": 13,
        "288": 13,
        "745": 13,
        "94": 14,
        "97": 14,
        "161": 14,
        "299": 14,
        "496": 14,
        "518": 14,
        "627": 14,
        "676": 14,
        "770": 14,
        "917": 14,
        "402": 15,
        "403": 15,
        "652": 15,
        "268": 16,
        "647": 16,
        "302": 17,
        "747": 17,
        "872": 17,
        "81": 18,
        "234": 18,
        "180": 19,
        "390": 19,
        "61": 20,
        "139": 20,
        "99": 21,
        "142": 21,
        "214": 21,
        "275": 21,
        "367": 21,
        "393": 21,
        "448": 21,
        "480": 21,
        "619": 21,
        "631": 21,
        "673": 21,
        "788": 21,
        "829": 21,
        "146": 22,
        "150": 22,
        "64": 23,
        "812": 23,
        "27": 24,
        "394": 24,
        "807": 24,
        "41": 25,
        "144": 25,
        "354": 25,
        "418": 25,
        "907": 25,
        "335": 26,
        "668": 26,
        "247": 27,
        "315": 27,
        "547": 27,
        "23": 28,
        "46": 28,
        "47": 28,
        "300": 28,
        "341": 28,
        "484": 28,
        "486": 28,
        "130": 29,
        "420": 29,
        "444": 30,
        "842": 30,
        "11": 31,
        "467": 31,
        "920": 31,
        "218": 32,
        "981": 32,
        "8": 33,
        "694": 33,
        "72": 34,
        "737": 34,
        "374": 35,
        "974": 35,
        "317": 36,
        "1018": 36,
        "205": 37,
        "452": 37,
        "91": 38,
        "687": 38,
        "50": 39,
        "751": 39,
        "185": 40,
        "632": 40,
        "305": 41,
        "329": 41,
        "623": 41,
        "31": 42,
        "790": 42,
        "987": 43,
        "1002": 43,
        "462": 44,
        "797": 44,
        "137": 45,
        "499": 45,
        "217": 46,
        "569": 46,
        "1": 47,
        "19": 47,
        "131": 48,
        "765": 48,
        "314": 49,
        "659": 49,
        "209": 50,
        "843": 50,
        "685": 51,
        "944": 51,
        "522": 52,
        "681": 52,
        "169": 53,
        "596": 53,
        "39": 54,
        "232": 54,
        "334": 54,
        "648": 55,
        "769": 55,
        "118": 56,
        "617": 56,
        "114": 57,
        "453": 57,
        "279": 58,
        "552": 58,
        "1023": 59,
        "1022": 60,
        "1021": 61,
        "1020": 62,
        "1019": 63,
        "1017": 64,
        "1016": 65,
        "1015": 66,
        "1014": 67,
        "1013": 68,
        "1012": 69,
        "1011": 70,
        "1010": 71,
        "1009": 72,
        "1008": 73,
        "1007": 74,
        "1005": 75,
        "1004": 76,
        "1000": 77,
        "998": 78,
        "997": 79,
        "996": 80,
        "994": 81,
        "993": 82,
        "992": 83,
        "991": 84,
        "990": 85,
        "989": 86,
        "988": 87,
        "986": 88,
        "985": 89,
        "983": 90,
        "982": 91,
        "980": 92,
        "979": 93,
        "978": 94,
        "977": 95,
        "976": 96,
        "975": 97,
        "973": 98,
        "972": 99,
        "971": 100,
        "970": 101,
        "969": 102,
        "968": 103,
        "967": 104,
        "966": 105,
        "965": 106,
        "962": 107,
        "961": 108,
        "960": 109,
        "959": 110,
        "958": 111,
        "957": 112,
        "956": 113,
        "955": 114,
        "954": 115,
        "953": 116,
        "952": 117,
        "951": 118,
        "950": 119,
        "949": 120,
        "948": 121,
        "947": 122,
        "946": 123,
        "945": 124,
        "943": 125,
        "942": 126,
        "941": 127,
        "940": 128,
        "939": 129,
        "938": 130,
        "937": 131,
        "936": 132,
        "935": 133,
        "934": 134,
        "933": 135,
        "932": 136,
        "931": 137,
        "930": 138,
        "929": 139,
        "928": 140,
        "927": 141,
        "926": 142,
        "925": 143,
        "924": 144,
        "923": 145,
        "922": 146,
        "921": 147,
        "919": 148,
        "918": 149,
        "915": 150,
        "914": 151,
        "913": 152,
        "912": 153,
        "911": 154,
        "910": 155,
        "909": 156,
        "908": 157,
        "906": 158,
        "905": 159,
        "904": 160,
        "903": 161,
        "902": 162,
        "901": 163,
        "900": 164,
        "899": 165,
        "898": 166,
        "897": 167,
        "896": 168,
        "895": 169,
        "894": 170,
        "893": 171,
        "891": 172,
        "890": 173,
        "889": 174,
        "888": 175,
        "887": 176,
        "886": 177,
        "885": 178,
        "884": 179,
        "883": 180,
        "882": 181,
        "881": 182,
        "880": 183,
        "879": 184,
        "878": 185,
        "877": 186,
        "876": 187,
        "875": 188,
        "874": 189,
        "873": 190,
        "871": 191,
        "870": 192,
        "869": 193,
        "867": 194,
        "866": 195,
        "865": 196,
        "864": 197,
        "863": 198,
        "862": 199,
        "861": 200,
        "860": 201,
        "859": 202,
        "858": 203,
        "857": 204,
        "856": 205,
        "855": 206,
        "854": 207,
        "853": 208,
        "852": 209,
        "851": 210,
        "850": 211,
        "849": 212,
        "848": 213,
        "846": 214,
        "845": 215,
        "844": 216,
        "841": 217,
        "840": 218,
        "839": 219,
        "838": 220,
        "837": 221,
        "836": 222,
        "835": 223,
        "834": 224,
        "832": 225,
        "831": 226,
        "830": 227,
        "828": 228,
        "827": 229,
        "826": 230,
        "825": 231,
        "824": 232,
        "823": 233,
        "822": 234,
        "821": 235,
        "820": 236,
        "819": 237,
        "818": 238,
        "817": 239,
        "816": 240,
        "815": 241,
        "814": 242,
        "813": 243,
        "811": 244,
        "810": 245,
        "809": 246,
        "808": 247,
        "806": 248,
        "805": 249,
        "804": 250,
        "803": 251,
        "802": 252,
        "801": 253,
        "800": 254,
        "799": 255,
        "798": 256,
        "796": 257,
        "795": 258,
        "792": 259,
        "791": 260,
        "789": 261,
        "787": 262,
        "786": 263,
        "785": 264,
        "784": 265,
        "782": 266,
        "781": 267,
        "780": 268,
        "778": 269,
        "777": 270,
        "776": 271,
        "775": 272,
        "774": 273,
        "773": 274,
        "772": 275,
        "771": 276,
        "768": 277,
        "767": 278,
        "766": 279,
        "764": 280,
        "763": 281,
        "762": 282,
        "761": 283,
        "760": 284,
        "759": 285,
        "758": 286,
        "757": 287,
        "756": 288,
        "755": 289,
        "754": 290,
        "753": 291,
        "752": 292,
        "750": 293,
        "749": 294,
        "748": 295,
        "746": 296,
        "744": 297,
        "743": 298,
        "742": 299,
        "741": 300,
        "740": 301,
        "739": 302,
        "738": 303,
        "736": 304,
        "735": 305,
        "733": 306,
        "732": 307,
        "731": 308,
        "730": 309,
        "729": 310,
        "728": 311,
        "727": 312,
        "726": 313,
        "725": 314,
        "724": 315,
        "723": 316,
        "722": 317,
        "721": 318,
        "720": 319,
        "719": 320,
        "718": 321,
        "717": 322,
        "716": 323,
        "715": 324,
        "714": 325,
        "713": 326,
        "712": 327,
        "711": 328,
        "710": 329,
        "709": 330,
        "708": 331,
        "707": 332,
        "706": 333,
        "705": 334,
        "704": 335,
        "703": 336,
        "702": 337,
        "701": 338,
        "700": 339,
        "699": 340,
        "698": 341,
        "697": 342,
        "696": 343,
        "695": 344,
        "693": 345,
        "692": 346,
        "691": 347,
        "690": 348,
        "689": 349,
        "688": 350,
        "686": 351,
        "684": 352,
        "683": 353,
        "682": 354,
        "680": 355,
        "679": 356,
        "678": 357,
        "677": 358,
        "675": 359,
        "674": 360,
        "672": 361,
        "671": 362,
        "670": 363,
        "669": 364,
        "667": 365,
        "666": 366,
        "665": 367,
        "664": 368,
        "663": 369,
        "662": 370,
        "661": 371,
        "660": 372,
        "658": 373,
        "657": 374,
        "655": 375,
        "654": 376,
        "653": 377,
        "651": 378,
        "650": 379,
        "649": 380,
        "646": 381,
        "645": 382,
        "644": 383,
        "643": 384,
        "642": 385,
        "641": 386,
        "640": 387,
        "639": 388,
        "638": 389,
        "637": 390,
        "636": 391,
        "635": 392,
        "634": 393,
        "633": 394,
        "630": 395,
        "629": 396,
        "628": 397,
        "626": 398,
        "625": 399,
        "624": 400,
        "622": 401,
        "621": 402,
        "620": 403,
        "618": 404,
        "616": 405,
        "615": 406,
        "614": 407,
        "613": 408,
        "612": 409,
        "610": 410,
        "609": 411,
        "608": 412,
        "607": 413,
        "606": 414,
        "605": 415,
        "604": 416,
        "603": 417,
        "602": 418,
        "601": 419,
        "600": 420,
        "599": 421,
        "598": 422,
        "597": 423,
        "595": 424,
        "594": 425,
        "593": 426,
        "592": 427,
        "591": 428,
        "590": 429,
        "589": 430,
        "588": 431,
        "587": 432,
        "586": 433,
        "585": 434,
        "584": 435,
        "583": 436,
        "582": 437,
        "580": 438,
        "579": 439,
        "578": 440,
        "577": 441,
        "576": 442,
        "575": 443,
        "574": 444,
        "573": 445,
        "572": 446,
        "571": 447,
        "570": 448,
        "568": 449,
        "567": 450,
        "566": 451,
        "565": 452,
        "563": 453,
        "562": 454,
        "561": 455,
        "560": 456,
        "559": 457,
        "558": 458,
        "557": 459,
        "556": 460,
        "555": 461,
        "554": 462,
        "553": 463,
        "551": 464,
        "550": 465,
        "549": 466,
        "548": 467,
        "546": 468,
        "545": 469,
        "544": 470,
        "543": 471,
        "542": 472,
        "541": 473,
        "540": 474,
        "539": 475,
        "538": 476,
        "537": 477,
        "536": 478,
        "535": 479,
        "533": 480,
        "532": 481,
        "530": 482,
        "529": 483,
        "528": 484,
        "527": 485,
        "526": 486,
        "525": 487,
        "524": 488,
        "523": 489,
        "521": 490,
        "519": 491,
        "517": 492,
        "516": 493,
        "515": 494,
        "514": 495,
        "513": 496,
        "512": 497,
        "511": 498,
        "510": 499,
        "509": 500,
        "508": 501,
        "507": 502,
        "506": 503,
        "505": 504,
        "504": 505,
        "503": 506,
        "502": 507,
        "501": 508,
        "497": 509,
        "495": 510,
        "494": 511,
        "493": 512,
        "492": 513,
        "491": 514,
        "489": 515,
        "485": 516,
        "483": 517,
        "482": 518,
        "481": 519,
        "479": 520,
        "478": 521,
        "477": 522,
        "476": 523,
        "475": 524,
        "474": 525,
        "473": 526,
        "472": 527,
        "471": 528,
        "470": 529,
        "469": 530,
        "468": 531,
        "466": 532,
        "465": 533,
        "464": 534,
        "463": 535,
        "460": 536,
        "459": 537,
        "458": 538,
        "457": 539,
        "456": 540,
        "455": 541,
        "454": 542,
        "451": 543,
        "450": 544,
        "449": 545,
        "447": 546,
        "446": 547,
        "445": 548,
        "443": 549,
        "442": 550,
        "441": 551,
        "439": 552,
        "438": 553,
        "436": 554,
        "434": 555,
        "433": 556,
        "432": 557,
        "431": 558,
        "430": 559,
        "429": 560,
        "428": 561,
        "427": 562,
        "426": 563,
        "425": 564,
        "424": 565,
        "422": 566,
        "421": 567,
        "419": 568,
        "417": 569,
        "416": 570,
        "414": 571,
        "413": 572,
        "412": 573,
        "411": 574,
        "410": 575,
        "409": 576,
        "408": 577,
        "407": 578,
        "406": 579,
        "405": 580,
        "404": 581,
        "401": 582,
        "400": 583,
        "399": 584,
        "398": 585,
        "397": 586,
        "396": 587,
        "395": 588,
        "392": 589,
        "391": 590,
        "388": 591,
        "387": 592,
        "386": 593,
        "385": 594,
        "384": 595,
        "383": 596,
        "382": 597,
        "381": 598,
        "380": 599,
        "379": 600,
        "378": 601,
        "377": 602,
        "376": 603,
        "375": 604,
        "373": 605,
        "372": 606,
        "371": 607,
        "369": 608,
        "368": 609,
        "366": 610,
        "365": 611,
        "364": 612,
        "363": 613,
        "362": 614,
        "361": 615,
        "360": 616,
        "359": 617,
        "358": 618,
        "357": 619,
        "356": 620,
        "355": 621,
        "353": 622,
        "352": 623,
        "351": 624,
        "350": 625,
        "349": 626,
        "348": 627,
        "347": 628,
        "345": 629,
        "344": 630,
        "343": 631,
        "342": 632,
        "340": 633,
        "339": 634,
        "338": 635,
        "337": 636,
        "336": 637,
        "333": 638,
        "332": 639,
        "331": 640,
        "328": 641,
        "327": 642,
        "326": 643,
        "325": 644,
        "324": 645,
        "323": 646,
        "322": 647,
        "321": 648,
        "320": 649,
        "319": 650,
        "318": 651,
        "316": 652,
        "313": 653,
        "312": 654,
        "311": 655,
        "310": 656,
        "309": 657,
        "308": 658,
        "307": 659,
        "306": 660,
        "304": 661,
        "303": 662,
        "301": 663,
        "298": 664,
        "297": 665,
        "296": 666,
        "295": 667,
        "293": 668,
        "292": 669,
        "291": 670,
        "290": 671,
        "289": 672,
        "287": 673,
        "286": 674,
        "285": 675,
        "284": 676,
        "283": 677,
        "282": 678,
        "281": 679,
        "280": 680,
        "278": 681,
        "277": 682,
        "276": 683,
        "274": 684,
        "273": 685,
        "272": 686,
        "271": 687,
        "270": 688,
        "269": 689,
        "267": 690,
        "266": 691,
        "265": 692,
        "264": 693,
        "263": 694,
        "262": 695,
        "260": 696,
        "259": 697,
        "258": 698,
        "257": 699,
        "256": 700,
        "255": 701,
        "254": 702,
        "253": 703,
        "252": 704,
        "251": 705,
        "250": 706,
        "249": 707,
        "248": 708,
        "244": 709,
        "242": 710,
        "241": 711,
        "240": 712,
        "239": 713,
        "238": 714,
        "236": 715,
        "235": 716,
        "231": 717,
        "230": 718,
        "229": 719,
        "228": 720,
        "227": 721,
        "226": 722,
        "225": 723,
        "224": 724,
        "223": 725,
        "222": 726,
        "221": 727,
        "220": 728,
        "219": 729,
        "215": 730,
        "213": 731,
        "212": 732,
        "211": 733,
        "210": 734,
        "208": 735,
        "207": 736,
        "206": 737,
        "204": 738,
        "203": 739,
        "202": 740,
        "200": 741,
        "199": 742,
        "198": 743,
        "197": 744,
        "196": 745,
        "195": 746,
        "194": 747,
        "193": 748,
        "192": 749,
        "191": 750,
        "190": 751,
        "189": 752,
        "188": 753,
        "187": 754,
        "184": 755,
        "183": 756,
        "182": 757,
        "179": 758,
        "178": 759,
        "177": 760,
        "176": 761,
        "175": 762,
        "174": 763,
        "173": 764,
        "172": 765,
        "170": 766,
        "168": 767,
        "167": 768,
        "166": 769,
        "165": 770,
        "164": 771,
        "163": 772,
        "162": 773,
        "160": 774,
        "158": 775,
        "157": 776,
        "156": 777,
        "155": 778,
        "154": 779,
        "153": 780,
        "152": 781,
        "151": 782,
        "149": 783,
        "148": 784,
        "147": 785,
        "145": 786,
        "143": 787,
        "141": 788,
        "140": 789,
        "138": 790,
        "136": 791,
        "135": 792,
        "134": 793,
        "133": 794,
        "132": 795,
        "129": 796,
        "128": 797,
        "127": 798,
        "126": 799,
        "125": 800,
        "124": 801,
        "123": 802,
        "122": 803,
        "121": 804,
        "120": 805,
        "119": 806,
        "117": 807,
        "116": 808,
        "115": 809,
        "113": 810,
        "112": 811,
        "110": 812,
        "109": 813,
        "108": 814,
        "107": 815,
        "106": 816,
        "105": 817,
        "104": 818,
        "103": 819,
        "102": 820,
        "101": 821,
        "100": 822,
        "98": 823,
        "96": 824,
        "95": 825,
        "92": 826,
        "90": 827,
        "89": 828,
        "88": 829,
        "87": 830,
        "86": 831,
        "85": 832,
        "84": 833,
        "83": 834,
        "80": 835,
        "79": 836,
        "78": 837,
        "77": 838,
        "76": 839,
        "75": 840,
        "74": 841,
        "73": 842,
        "71": 843,
        "70": 844,
        "69": 845,
        "68": 846,
        "67": 847,
        "66": 848,
        "65": 849,
        "63": 850,
        "62": 851,
        "60": 852,
        "59": 853,
        "58": 854,
        "57": 855,
        "56": 856,
        "55": 857,
        "54": 858,
        "53": 859,
        "52": 860,
        "51": 861,
        "49": 862,
        "48": 863,
        "45": 864,
        "44": 865,
        "43": 866,
        "40": 867,
        "38": 868,
        "37": 869,
        "36": 870,
        "35": 871,
        "34": 872,
        "33": 873,
        "32": 874,
        "30": 875,
        "29": 876,
        "28": 877,
        "26": 878,
        "24": 879,
        "22": 880,
        "21": 881,
        "20": 882,
        "17": 883,
        "16": 884,
        "15": 885,
        "14": 886,
        "13": 887,
        "12": 888,
        "9": 889,
        "6": 890,
        "5": 891,
        "4": 892,
        "3": 893,
        "2": 894,
        "0": 895
    }
}