{
    "dataset": "cifar10",
    "clustering_method": "kmeans",
    "repr_method": "max",
    "partition_method": "square",
    "num_partitions": 2,
    "k": 120,
    "sub_k": 128,
    "nnac": {
        "38": 0,
        "61": 0,
        "86": 1,
        "98": 1,
        "40": 2,
        "104": 2,
        "9": 3,
        "96": 3,
        "1": 4,
        "108": 4,
        "16": 5,
        "77": 5,
        "64": 6,
        "118": 6,
        "5": 7,
        "75": 7,
        "127": 8,
        "126": 9,
        "125": 10,
        "124": 11,
        "123": 12,
        "122": 13,
        "121": 14,
        "120": 15,
        "119": 16,
        "117": 17,
        "116": 18,
        "115": 19,
        "114": 20,
        "113": 21,
        "112": 22,
        "111": 23,
        "110": 24,
        "109": 25,
        "107": 26,
        "106": 27,
        "105": 28,
        "103": 29,
        "102": 30,
        "101": 31,
        "100": 32,
        "99": 33,
        "97": 34,
        "95": 35,
        "94": 36,
        "93": 37,
        "92": 38,
        "91": 39,
        "90": 40,
        "89": 41,
        "88": 42,
        "87": 43,
        "85": 44,
        "84": 45,
        "83": 46,
        "82": 47,
        "81": 48,
        "80": 49,
        "79": 50,
        "78": 51,
        "76": 52,
        "74": 53,
        "73": 54,
        "72": 55,
        "71": 56,
        "70": 57,
        "69": 58,
        "68": 59,
        "67": 60,
        "66": 61,
        "65": 62,
        "63": 63,
        "62": 64,
        "60": 65,
        "59": 66,
        "58": 67,
        "57": 68,
        "56": 69,
        "55": 70,
        "54": 71,
        "53": 72,
        "52": 73,
        "51": 74,
        "50": 75,
        "49": 76,
        "48": 77,
        "47": 78,
        "46": 79,
        "45": 80,
        "44": 81,
        "43": 82,
        "42": 83,
        "41": 84,
        "39": 85,
        "37": 86,
        "36": 87,
        "35": 88,
        "34": 89,
        "33": 90,
        "32": 91,
        "31": 92,
        "30": 93,
        "29": 94,
        "28": 95,
        "27": 96,
        "26": 97,
        "25": 98,
        "24": 99,
        "23": 100,
        "22": 101,
        "21": 102,
        "20": 103,
        "19": 104,
        "18": 105,
        "17": 106,
        "15": 107,
        "14": 108,
        "13": 109,
        "12": 110,
        "11": 111,
        "10": 112,
        "8": 113,
        "7": 114,
        "6": 115,
        "4": 116,
        "3": 117,
        "2": 118,
        "0": 119
    }
}