{
    "dataset": "cifar10",
    "clustering_method": "kmeans",
    "repr_method": "max",
    "partition_method": "square",
    "num_partitions": 2,
    "k": 160,
    "sub_k": 256,
    "nnac": {
        "0": 0,
        "128": 0,
        "130": 0,
        "134": 0,
        "7": 0,
        "15": 0,
        "16": 0,
        "18": 0,
        "21": 0,
        "25": 0,
        "184": 0,
        "65": 0,
        "195": 0,
        "72": 0,
        "203": 0,
        "207": 0,
        "208": 0,
        "220": 0,
        "99": 0,
        "101": 0,
        "232": 0,
        "112": 0,
        "1": 1,
        "124": 1,
        "68": 1,
        "2": 2,
        "13": 2,
        "143": 2,
        "150": 2,
        "24": 2,
        "31": 2,
        "165": 2,
        "52": 2,
        "53": 2,
        "185": 2,
        "59": 2,
        "64": 2,
        "88": 2,
        "217": 2,
        "218": 2,
        "91": 2,
        "92": 2,
        "104": 2,
        "106": 2,
        "108": 2,
        "237": 2,
        "109": 2,
        "114": 2,
        "116": 2,
        "122": 2,
        "127": 2,
        "14": 3,
        "144": 3,
        "6": 3,
        "175": 3,
        "192": 4,
        "225": 4,
        "9": 4,
        "201": 4,
        "204": 4,
        "77": 4,
        "78": 4,
        "206": 4,
        "80": 4,
        "79": 4,
        "29": 4,
        "19": 4,
        "125": 4,
        "186": 4,
        "93": 4,
        "32": 5,
        "120": 5,
        "34": 6,
        "36": 6,
        "37": 7,
        "176": 7,
        "62": 7,
        "166": 8,
        "199": 8,
        "40": 8,
        "81": 8,
        "84": 8,
        "87": 8,
        "44": 9,
        "70": 9,
        "45": 10,
        "135": 10,
        "48": 11,
        "67": 11,
        "51": 12,
        "193": 12,
        "105": 13,
        "235": 13,
        "61": 13,
        "63": 14,
        "161": 14,
        "75": 15,
        "246": 15,
        "85": 16,
        "252": 16,
        "86": 17,
        "167": 17,
        "94": 18,
        "233": 18,
        "113": 19,
        "222": 19,
        "118": 20,
        "179": 20,
        "132": 21,
        "162": 21,
        "140": 22,
        "181": 22,
        "148": 23,
        "213": 23,
        "156": 24,
        "229": 24,
        "223": 24,
        "158": 25,
        "245": 25,
        "236": 26,
        "241": 26,
        "197": 26,
        "230": 27,
        "247": 27,
        "3": 28,
        "4": 29,
        "5": 30,
        "8": 31,
        "10": 32,
        "11": 33,
        "12": 34,
        "17": 35,
        "20": 36,
        "22": 37,
        "23": 38,
        "26": 39,
        "27": 40,
        "28": 41,
        "30": 42,
        "33": 43,
        "35": 44,
        "38": 45,
        "39": 46,
        "41": 47,
        "42": 48,
        "43": 49,
        "46": 50,
        "47": 51,
        "49": 52,
        "50": 53,
        "54": 54,
        "55": 55,
        "56": 56,
        "57": 57,
        "58": 58,
        "60": 59,
        "66": 60,
        "69": 61,
        "71": 62,
        "73": 63,
        "74": 64,
        "76": 65,
        "82": 66,
        "83": 67,
        "89": 68,
        "90": 69,
        "95": 70,
        "96": 71,
        "97": 72,
        "98": 73,
        "100": 74,
        "102": 75,
        "103": 76,
        "107": 77,
        "110": 78,
        "111": 79,
        "115": 80,
        "117": 81,
        "119": 82,
        "121": 83,
        "123": 84,
        "126": 85,
        "129": 86,
        "131": 87,
        "133": 88,
        "136": 89,
        "137": 90,
        "138": 91,
        "139": 92,
        "141": 93,
        "142": 94,
        "145": 95,
        "146": 96,
        "147": 97,
        "149": 98,
        "151": 99,
        "152": 100,
        "153": 101,
        "154": 102,
        "155": 103,
        "157": 104,
        "159": 105,
        "160": 106,
        "163": 107,
        "164": 108,
        "168": 109,
        "169": 110,
        "170": 111,
        "171": 112,
        "172": 113,
        "173": 114,
        "174": 115,
        "177": 116,
        "178": 117,
        "180": 118,
        "182": 119,
        "183": 120,
        "187": 121,
        "188": 122,
        "189": 123,
        "190": 124,
        "191": 125,
        "194": 126,
        "196": 127,
        "198": 128,
        "200": 129,
        "202": 130,
        "205": 131,
        "209": 132,
        "210": 133,
        "211": 134,
        "212": 135,
        "214": 136,
        "215": 137,
        "216": 138,
        "219": 139,
        "221": 140,
        "224": 141,
        "226": 142,
        "227": 143,
        "228": 144,
        "231": 145,
        "234": 146,
        "238": 147,
        "239": 148,
        "240": 149,
        "242": 150,
        "243": 151,
        "244": 152,
        "248": 153,
        "249": 154,
        "250": 155,
        "251": 156,
        "253": 157,
        "254": 158,
        "255": 159
    }
}