{
    "dataset": "cifar10",
    "clustering_method": "kmeans",
    "repr_method": "max",
    "partition_method": "square",
    "num_partitions": 2,
    "k": 576,
    "sub_k": 1024,
    "nnac": {
        "63": 0,
        "679": 0,
        "35": 1,
        "56": 1,
        "80": 1,
        "87": 1,
        "91": 1,
        "95": 1,
        "158": 1,
        "214": 1,
        "246": 1,
        "390": 1,
        "428": 1,
        "450": 1,
        "460": 1,
        "507": 1,
        "520": 1,
        "532": 1,
        "559": 1,
        "579": 1,
        "584": 1,
        "608": 1,
        "717": 1,
        "874": 1,
        "981": 1,
        "992": 1,
        "3": 2,
        "4": 2,
        "11": 2,
        "18": 2,
        "22": 2,
        "30": 2,
        "38": 2,
        "41": 2,
        "46": 2,
        "47": 2,
        "51": 2,
        "57": 2,
        "90": 2,
        "100": 2,
        "101": 2,
        "115": 2,
        "128": 2,
        "141": 2,
        "144": 2,
        "154": 2,
        "160": 2,
        "162": 2,
        "172": 2,
        "177": 2,
        "178": 2,
        "191": 2,
        "203": 2,
        "206": 2,
        "209": 2,
        "211": 2,
        "220": 2,
        "221": 2,
        "236": 2,
        "242": 2,
        "245": 2,
        "251": 2,
        "258": 2,
        "264": 2,
        "271": 2,
        "278": 2,
        "295": 2,
        "303": 2,
        "304": 2,
        "306": 2,
        "310": 2,
        "311": 2,
        "315": 2,
        "317": 2,
        "330": 2,
        "353": 2,
        "364": 2,
        "365": 2,
        "368": 2,
        "392": 2,
        "397": 2,
        "401": 2,
        "408": 2,
        "411": 2,
        "412": 2,
        "414": 2,
        "429": 2,
        "438": 2,
        "451": 2,
        "459": 2,
        "473": 2,
        "478": 2,
        "499": 2,
        "500": 2,
        "508": 2,
        "521": 2,
        "546": 2,
        "549": 2,
        "551": 2,
        "567": 2,
        "580": 2,
        "602": 2,
        "604": 2,
        "606": 2,
        "614": 2,
        "644": 2,
        "646": 2,
        "648": 2,
        "651": 2,
        "657": 2,
        "667": 2,
        "669": 2,
        "673": 2,
        "692": 2,
        "714": 2,
        "719": 2,
        "732": 2,
        "761": 2,
        "762": 2,
        "766": 2,
        "775": 2,
        "776": 2,
        "781": 2,
        "783": 2,
        "785": 2,
        "786": 2,
        "797": 2,
        "813": 2,
        "856": 2,
        "864": 2,
        "878": 2,
        "885": 2,
        "897": 2,
        "906": 2,
        "912": 2,
        "917": 2,
        "926": 2,
        "939": 2,
        "941": 2,
        "956": 2,
        "964": 2,
        "1012": 2,
        "1018": 2,
        "1021": 2,
        "19": 3,
        "625": 3,
        "633": 3,
        "986": 3,
        "43": 4,
        "109": 4,
        "527": 4,
        "706": 4,
        "769": 4,
        "916": 4,
        "130": 5,
        "324": 5,
        "713": 5,
        "16": 6,
        "17": 6,
        "20": 6,
        "31": 6,
        "45": 6,
        "49": 6,
        "67": 6,
        "75": 6,
        "81": 6,
        "89": 6,
        "98": 6,
        "152": 6,
        "155": 6,
        "161": 6,
        "198": 6,
        "243": 6,
        "296": 6,
        "309": 6,
        "312": 6,
        "326": 6,
        "335": 6,
        "358": 6,
        "376": 6,
        "387": 6,
        "396": 6,
        "399": 6,
        "402": 6,
        "407": 6,
        "410": 6,
        "463": 6,
        "472": 6,
        "495": 6,
        "542": 6,
        "557": 6,
        "565": 6,
        "636": 6,
        "640": 6,
        "671": 6,
        "683": 6,
        "688": 6,
        "753": 6,
        "771": 6,
        "782": 6,
        "790": 6,
        "791": 6,
        "794": 6,
        "799": 6,
        "809": 6,
        "825": 6,
        "831": 6,
        "843": 6,
        "846": 6,
        "860": 6,
        "876": 6,
        "877": 6,
        "895": 6,
        "928": 6,
        "932": 6,
        "947": 6,
        "966": 6,
        "976": 6,
        "999": 6,
        "1004": 6,
        "1008": 6,
        "1011": 6,
        "1015": 6,
        "54": 7,
        "173": 7,
        "297": 7,
        "441": 7,
        "534": 7,
        "607": 7,
        "730": 7,
        "320": 8,
        "691": 8,
        "707": 8,
        "712": 8,
        "232": 9,
        "331": 9,
        "426": 9,
        "449": 9,
        "570": 9,
        "589": 9,
        "988": 9,
        "65": 10,
        "336": 10,
        "971": 10,
        "10": 11,
        "21": 11,
        "32": 11,
        "60": 11,
        "212": 11,
        "215": 11,
        "219": 11,
        "265": 11,
        "313": 11,
        "342": 11,
        "346": 11,
        "352": 11,
        "404": 11,
        "420": 11,
        "422": 11,
        "423": 11,
        "424": 11,
        "512": 11,
        "545": 11,
        "560": 11,
        "639": 11,
        "641": 11,
        "647": 11,
        "663": 11,
        "741": 11,
        "746": 11,
        "768": 11,
        "827": 11,
        "893": 11,
        "930": 11,
        "935": 11,
        "965": 11,
        "978": 11,
        "9": 12,
        "133": 12,
        "367": 12,
        "672": 12,
        "690": 12,
        "989": 12,
        "995": 12,
        "176": 13,
        "200": 13,
        "248": 13,
        "257": 13,
        "356": 13,
        "374": 13,
        "430": 13,
        "446": 13,
        "564": 13,
        "601": 13,
        "837": 13,
        "573": 14,
        "850": 14,
        "950": 14,
        "52": 15,
        "73": 15,
        "96": 15,
        "122": 15,
        "149": 15,
        "166": 15,
        "170": 15,
        "193": 15,
        "196": 15,
        "225": 15,
        "379": 15,
        "415": 15,
        "418": 15,
        "445": 15,
        "467": 15,
        "490": 15,
        "501": 15,
        "503": 15,
        "509": 15,
        "515": 15,
        "574": 15,
        "623": 15,
        "666": 15,
        "678": 15,
        "682": 15,
        "731": 15,
        "743": 15,
        "792": 15,
        "807": 15,
        "883": 15,
        "905": 15,
        "907": 15,
        "919": 15,
        "957": 15,
        "480": 16,
        "697": 16,
        "8": 17,
        "815": 17,
        "859": 17,
        "984": 17,
        "227": 18,
        "482": 18,
        "107": 19,
        "114": 19,
        "77": 20,
        "963": 20,
        "186": 21,
        "752": 21,
        "134": 22,
        "183": 22,
        "611": 22,
        "40": 23,
        "105": 23,
        "169": 23,
        "241": 23,
        "393": 23,
        "493": 23,
        "516": 23,
        "533": 23,
        "658": 23,
        "796": 23,
        "839": 23,
        "126": 24,
        "135": 24,
        "283": 24,
        "892": 24,
        "718": 25,
        "764": 25,
        "103": 26,
        "194": 26,
        "909": 26,
        "305": 27,
        "596": 27,
        "333": 28,
        "524": 28,
        "635": 28,
        "696": 28,
        "226": 29,
        "756": 29,
        "168": 30,
        "321": 30,
        "64": 31,
        "240": 31,
        "252": 32,
        "758": 32,
        "417": 33,
        "514": 33,
        "911": 33,
        "25": 34,
        "497": 34,
        "26": 35,
        "757": 35,
        "594": 36,
        "656": 36,
        "99": 37,
        "398": 37,
        "119": 38,
        "199": 38,
        "208": 38,
        "531": 38,
        "566": 38,
        "817": 38,
        "370": 39,
        "619": 39,
        "182": 40,
        "195": 40,
        "745": 41,
        "867": 41,
        "5": 42,
        "645": 42,
        "763": 42,
        "237": 43,
        "502": 43,
        "681": 43,
        "842": 43,
        "268": 44,
        "558": 44,
        "638": 44,
        "106": 45,
        "151": 45,
        "328": 45,
        "577": 45,
        "431": 46,
        "818": 46,
        "66": 47,
        "572": 47,
        "800": 48,
        "922": 48,
        "951": 48,
        "539": 49,
        "920": 49,
        "458": 50,
        "488": 50,
        "189": 51,
        "437": 51,
        "675": 51,
        "72": 52,
        "249": 52,
        "990": 52,
        "140": 53,
        "179": 53,
        "650": 53,
        "725": 53,
        "167": 54,
        "470": 54,
        "486": 54,
        "811": 54,
        "97": 55,
        "123": 55,
        "323": 55,
        "338": 55,
        "510": 55,
        "511": 55,
        "582": 55,
        "590": 55,
        "840": 55,
        "924": 55,
        "347": 56,
        "585": 56,
        "914": 56,
        "188": 57,
        "298": 57,
        "229": 58,
        "949": 58,
        "299": 59,
        "812": 59,
        "901": 59,
        "998": 59,
        "76": 60,
        "300": 60,
        "1016": 60,
        "448": 61,
        "1017": 61,
        "159": 62,
        "750": 62,
        "145": 63,
        "293": 63,
        "44": 64,
        "85": 64,
        "554": 64,
        "803": 64,
        "174": 65,
        "834": 65,
        "0": 66,
        "425": 66,
        "238": 67,
        "259": 67,
        "433": 67,
        "547": 67,
        "760": 67,
        "855": 67,
        "184": 68,
        "588": 68,
        "993": 68,
        "148": 69,
        "583": 69,
        "822": 70,
        "908": 70,
        "163": 71,
        "686": 71,
        "15": 72,
        "836": 72,
        "2": 73,
        "485": 73,
        "350": 74,
        "913": 74,
        "129": 75,
        "228": 75,
        "727": 75,
        "664": 76,
        "857": 76,
        "197": 77,
        "369": 77,
        "386": 77,
        "153": 78,
        "216": 78,
        "256": 79,
        "974": 79,
        "12": 80,
        "143": 80,
        "175": 80,
        "591": 80,
        "946": 80,
        "218": 81,
        "568": 81,
        "120": 82,
        "384": 82,
        "78": 83,
        "457": 83,
        "48": 84,
        "676": 84,
        "395": 85,
        "747": 85,
        "111": 86,
        "339": 86,
        "642": 87,
        "661": 87,
        "223": 88,
        "933": 88,
        "1023": 89,
        "1022": 90,
        "1020": 91,
        "1019": 92,
        "1014": 93,
        "1013": 94,
        "1010": 95,
        "1009": 96,
        "1007": 97,
        "1006": 98,
        "1005": 99,
        "1003": 100,
        "1002": 101,
        "1001": 102,
        "1000": 103,
        "997": 104,
        "996": 105,
        "994": 106,
        "991": 107,
        "987": 108,
        "985": 109,
        "983": 110,
        "982": 111,
        "980": 112,
        "979": 113,
        "977": 114,
        "975": 115,
        "973": 116,
        "972": 117,
        "970": 118,
        "969": 119,
        "968": 120,
        "967": 121,
        "962": 122,
        "961": 123,
        "960": 124,
        "959": 125,
        "958": 126,
        "955": 127,
        "954": 128,
        "953": 129,
        "952": 130,
        "948": 131,
        "945": 132,
        "944": 133,
        "943": 134,
        "942": 135,
        "940": 136,
        "938": 137,
        "937": 138,
        "936": 139,
        "934": 140,
        "931": 141,
        "929": 142,
        "927": 143,
        "925": 144,
        "923": 145,
        "921": 146,
        "918": 147,
        "915": 148,
        "910": 149,
        "904": 150,
        "903": 151,
        "902": 152,
        "900": 153,
        "899": 154,
        "898": 155,
        "896": 156,
        "894": 157,
        "891": 158,
        "890": 159,
        "889": 160,
        "888": 161,
        "887": 162,
        "886": 163,
        "884": 164,
        "882": 165,
        "881": 166,
        "880": 167,
        "879": 168,
        "875": 169,
        "873": 170,
        "872": 171,
        "871": 172,
        "870": 173,
        "869": 174,
        "868": 175,
        "866": 176,
        "865": 177,
        "863": 178,
        "862": 179,
        "861": 180,
        "858": 181,
        "854": 182,
        "853": 183,
        "852": 184,
        "851": 185,
        "849": 186,
        "848": 187,
        "847": 188,
        "845": 189,
        "844": 190,
        "841": 191,
        "838": 192,
        "835": 193,
        "833": 194,
        "832": 195,
        "830": 196,
        "829": 197,
        "828": 198,
        "826": 199,
        "824": 200,
        "823": 201,
        "821": 202,
        "820": 203,
        "819": 204,
        "816": 205,
        "814": 206,
        "810": 207,
        "808": 208,
        "806": 209,
        "805": 210,
        "804": 211,
        "802": 212,
        "801": 213,
        "798": 214,
        "795": 215,
        "793": 216,
        "789": 217,
        "788": 218,
        "787": 219,
        "784": 220,
        "780": 221,
        "779": 222,
        "778": 223,
        "777": 224,
        "774": 225,
        "773": 226,
        "772": 227,
        "770": 228,
        "767": 229,
        "765": 230,
        "759": 231,
        "755": 232,
        "754": 233,
        "751": 234,
        "749": 235,
        "748": 236,
        "744": 237,
        "742": 238,
        "740": 239,
        "739": 240,
        "738": 241,
        "737": 242,
        "736": 243,
        "735": 244,
        "734": 245,
        "733": 246,
        "729": 247,
        "728": 248,
        "726": 249,
        "724": 250,
        "723": 251,
        "722": 252,
        "721": 253,
        "720": 254,
        "716": 255,
        "715": 256,
        "711": 257,
        "710": 258,
        "709": 259,
        "708": 260,
        "705": 261,
        "704": 262,
        "703": 263,
        "702": 264,
        "701": 265,
        "700": 266,
        "699": 267,
        "698": 268,
        "695": 269,
        "694": 270,
        "693": 271,
        "689": 272,
        "687": 273,
        "685": 274,
        "684": 275,
        "680": 276,
        "677": 277,
        "674": 278,
        "670": 279,
        "668": 280,
        "665": 281,
        "662": 282,
        "660": 283,
        "659": 284,
        "655": 285,
        "654": 286,
        "653": 287,
        "652": 288,
        "649": 289,
        "643": 290,
        "637": 291,
        "634": 292,
        "632": 293,
        "631": 294,
        "630": 295,
        "629": 296,
        "628": 297,
        "627": 298,
        "626": 299,
        "624": 300,
        "622": 301,
        "621": 302,
        "620": 303,
        "618": 304,
        "617": 305,
        "616": 306,
        "615": 307,
        "613": 308,
        "612": 309,
        "610": 310,
        "609": 311,
        "605": 312,
        "603": 313,
        "600": 314,
        "599": 315,
        "598": 316,
        "597": 317,
        "595": 318,
        "593": 319,
        "592": 320,
        "587": 321,
        "586": 322,
        "581": 323,
        "578": 324,
        "576": 325,
        "575": 326,
        "571": 327,
        "569": 328,
        "563": 329,
        "562": 330,
        "561": 331,
        "556": 332,
        "555": 333,
        "553": 334,
        "552": 335,
        "550": 336,
        "548": 337,
        "544": 338,
        "543": 339,
        "541": 340,
        "540": 341,
        "538": 342,
        "537": 343,
        "536": 344,
        "535": 345,
        "530": 346,
        "529": 347,
        "528": 348,
        "526": 349,
        "525": 350,
        "523": 351,
        "522": 352,
        "519": 353,
        "518": 354,
        "517": 355,
        "513": 356,
        "506": 357,
        "505": 358,
        "504": 359,
        "498": 360,
        "496": 361,
        "494": 362,
        "492": 363,
        "491": 364,
        "489": 365,
        "487": 366,
        "484": 367,
        "483": 368,
        "481": 369,
        "479": 370,
        "477": 371,
        "476": 372,
        "475": 373,
        "474": 374,
        "471": 375,
        "469": 376,
        "468": 377,
        "466": 378,
        "465": 379,
        "464": 380,
        "462": 381,
        "461": 382,
        "456": 383,
        "455": 384,
        "454": 385,
        "453": 386,
        "452": 387,
        "447": 388,
        "444": 389,
        "443": 390,
        "442": 391,
        "440": 392,
        "439": 393,
        "436": 394,
        "435": 395,
        "434": 396,
        "432": 397,
        "427": 398,
        "421": 399,
        "419": 400,
        "416": 401,
        "413": 402,
        "409": 403,
        "406": 404,
        "405": 405,
        "403": 406,
        "400": 407,
        "394": 408,
        "391": 409,
        "389": 410,
        "388": 411,
        "385": 412,
        "383": 413,
        "382": 414,
        "381": 415,
        "380": 416,
        "378": 417,
        "377": 418,
        "375": 419,
        "373": 420,
        "372": 421,
        "371": 422,
        "366": 423,
        "363": 424,
        "362": 425,
        "361": 426,
        "360": 427,
        "359": 428,
        "357": 429,
        "355": 430,
        "354": 431,
        "351": 432,
        "349": 433,
        "348": 434,
        "345": 435,
        "344": 436,
        "343": 437,
        "341": 438,
        "340": 439,
        "337": 440,
        "334": 441,
        "332": 442,
        "329": 443,
        "327": 444,
        "325": 445,
        "322": 446,
        "319": 447,
        "318": 448,
        "316": 449,
        "314": 450,
        "308": 451,
        "307": 452,
        "302": 453,
        "301": 454,
        "294": 455,
        "292": 456,
        "291": 457,
        "290": 458,
        "289": 459,
        "288": 460,
        "287": 461,
        "286": 462,
        "285": 463,
        "284": 464,
        "282": 465,
        "281": 466,
        "280": 467,
        "279": 468,
        "277": 469,
        "276": 470,
        "275": 471,
        "274": 472,
        "273": 473,
        "272": 474,
        "270": 475,
        "269": 476,
        "267": 477,
        "266": 478,
        "263": 479,
        "262": 480,
        "261": 481,
        "260": 482,
        "255": 483,
        "254": 484,
        "253": 485,
        "250": 486,
        "247": 487,
        "244": 488,
        "239": 489,
        "235": 490,
        "234": 491,
        "233": 492,
        "231": 493,
        "230": 494,
        "224": 495,
        "222": 496,
        "217": 497,
        "213": 498,
        "210": 499,
        "207": 500,
        "205": 501,
        "204": 502,
        "202": 503,
        "201": 504,
        "192": 505,
        "190": 506,
        "187": 507,
        "185": 508,
        "181": 509,
        "180": 510,
        "171": 511,
        "165": 512,
        "164": 513,
        "157": 514,
        "156": 515,
        "150": 516,
        "147": 517,
        "146": 518,
        "142": 519,
        "139": 520,
        "138": 521,
        "137": 522,
        "136": 523,
        "132": 524,
        "131": 525,
        "127": 526,
        "125": 527,
        "124": 528,
        "121": 529,
        "118": 530,
        "117": 531,
        "116": 532,
        "113": 533,
        "112": 534,
        "110": 535,
        "108": 536,
        "104": 537,
        "102": 538,
        "94": 539,
        "93": 540,
        "92": 541,
        "88": 542,
        "86": 543,
        "84": 544,
        "83": 545,
        "82": 546,
        "79": 547,
        "74": 548,
        "71": 549,
        "70": 550,
        "69": 551,
        "68": 552,
        "62": 553,
        "61": 554,
        "59": 555,
        "58": 556,
        "55": 557,
        "53": 558,
        "50": 559,
        "42": 560,
        "39": 561,
        "37": 562,
        "36": 563,
        "34": 564,
        "33": 565,
        "29": 566,
        "28": 567,
        "27": 568,
        "24": 569,
        "23": 570,
        "14": 571,
        "13": 572,
        "7": 573,
        "6": 574,
        "1": 575
    }
}