{
    "dataset": "cifar100",
    "clustering_method": "kmeans",
    "repr_method": "max",
    "partition_method": "square",
    "num_partitions": 2,
    "k": 176,
    "sub_k": 256,
    "nnac": {
        "55": 0,
        "58": 0,
        "29": 1,
        "66": 1,
        "95": 1,
        "163": 1,
        "210": 1,
        "52": 2,
        "64": 2,
        "113": 2,
        "132": 2,
        "175": 2,
        "248": 2,
        "12": 3,
        "15": 3,
        "16": 3,
        "18": 3,
        "38": 3,
        "59": 3,
        "83": 3,
        "90": 3,
        "108": 3,
        "117": 3,
        "129": 3,
        "147": 3,
        "150": 3,
        "190": 3,
        "196": 3,
        "204": 3,
        "207": 3,
        "208": 3,
        "213": 3,
        "221": 3,
        "231": 3,
        "238": 3,
        "53": 4,
        "92": 4,
        "102": 4,
        "142": 4,
        "227": 4,
        "41": 5,
        "69": 5,
        "79": 5,
        "81": 5,
        "119": 5,
        "161": 5,
        "187": 5,
        "245": 5,
        "252": 5,
        "47": 6,
        "173": 6,
        "50": 7,
        "85": 7,
        "110": 7,
        "155": 7,
        "168": 7,
        "178": 7,
        "34": 8,
        "195": 8,
        "48": 9,
        "139": 9,
        "145": 9,
        "166": 9,
        "217": 9,
        "206": 10,
        "226": 10,
        "123": 11,
        "247": 11,
        "75": 12,
        "77": 12,
        "32": 13,
        "126": 13,
        "152": 13,
        "179": 13,
        "205": 13,
        "219": 13,
        "225": 13,
        "73": 14,
        "183": 14,
        "23": 15,
        "180": 15,
        "202": 15,
        "105": 16,
        "148": 16,
        "212": 16,
        "21": 17,
        "232": 17,
        "24": 18,
        "37": 18,
        "61": 18,
        "65": 18,
        "89": 19,
        "109": 19,
        "233": 19,
        "10": 20,
        "101": 20,
        "4": 21,
        "14": 21,
        "93": 22,
        "121": 22,
        "236": 23,
        "251": 23,
        "6": 24,
        "228": 24,
        "86": 25,
        "114": 25,
        "255": 26,
        "254": 27,
        "253": 28,
        "250": 29,
        "249": 30,
        "246": 31,
        "244": 32,
        "243": 33,
        "242": 34,
        "241": 35,
        "240": 36,
        "239": 37,
        "237": 38,
        "235": 39,
        "234": 40,
        "230": 41,
        "229": 42,
        "224": 43,
        "223": 44,
        "222": 45,
        "220": 46,
        "218": 47,
        "216": 48,
        "215": 49,
        "214": 50,
        "211": 51,
        "209": 52,
        "203": 53,
        "201": 54,
        "200": 55,
        "199": 56,
        "198": 57,
        "197": 58,
        "194": 59,
        "193": 60,
        "192": 61,
        "191": 62,
        "189": 63,
        "188": 64,
        "186": 65,
        "185": 66,
        "184": 67,
        "182": 68,
        "181": 69,
        "177": 70,
        "176": 71,
        "174": 72,
        "172": 73,
        "171": 74,
        "170": 75,
        "169": 76,
        "167": 77,
        "165": 78,
        "164": 79,
        "162": 80,
        "160": 81,
        "159": 82,
        "158": 83,
        "157": 84,
        "156": 85,
        "154": 86,
        "153": 87,
        "151": 88,
        "149": 89,
        "146": 90,
        "144": 91,
        "143": 92,
        "141": 93,
        "140": 94,
        "138": 95,
        "137": 96,
        "136": 97,
        "135": 98,
        "134": 99,
        "133": 100,
        "131": 101,
        "130": 102,
        "128": 103,
        "127": 104,
        "125": 105,
        "124": 106,
        "122": 107,
        "120": 108,
        "118": 109,
        "116": 110,
        "115": 111,
        "112": 112,
        "111": 113,
        "107": 114,
        "106": 115,
        "104": 116,
        "103": 117,
        "100": 118,
        "99": 119,
        "98": 120,
        "97": 121,
        "96": 122,
        "94": 123,
        "91": 124,
        "88": 125,
        "87": 126,
        "84": 127,
        "82": 128,
        "80": 129,
        "78": 130,
        "76": 131,
        "74": 132,
        "72": 133,
        "71": 134,
        "70": 135,
        "68": 136,
        "67": 137,
        "63": 138,
        "62": 139,
        "60": 140,
        "57": 141,
        "56": 142,
        "54": 143,
        "51": 144,
        "49": 145,
        "46": 146,
        "45": 147,
        "44": 148,
        "43": 149,
        "42": 150,
        "40": 151,
        "39": 152,
        "36": 153,
        "35": 154,
        "33": 155,
        "31": 156,
        "30": 157,
        "28": 158,
        "27": 159,
        "26": 160,
        "25": 161,
        "22": 162,
        "20": 163,
        "19": 164,
        "17": 165,
        "13": 166,
        "11": 167,
        "9": 168,
        "8": 169,
        "7": 170,
        "5": 171,
        "3": 172,
        "2": 173,
        "1": 174,
        "0": 175
    }
}