{
    "dataset": "cifar10",
    "clustering_method": "kmeans",
    "repr_method": "max",
    "partition_method": "square",
    "num_partitions": 2,
    "k": 416,
    "sub_k": 512,
    "nnac": {
        "4": 0,
        "257": 0,
        "262": 0,
        "269": 0,
        "272": 0,
        "405": 0,
        "23": 0,
        "284": 0,
        "412": 0,
        "156": 0,
        "293": 0,
        "39": 0,
        "424": 0,
        "426": 0,
        "304": 0,
        "305": 0,
        "307": 0,
        "180": 0,
        "52": 0,
        "447": 0,
        "466": 0,
        "88": 0,
        "345": 0,
        "94": 0,
        "227": 0,
        "100": 0,
        "232": 0,
        "488": 0,
        "233": 0,
        "105": 0,
        "108": 0,
        "246": 0,
        "123": 0,
        "7": 1,
        "20": 1,
        "8": 2,
        "151": 2,
        "343": 2,
        "119": 2,
        "15": 3,
        "67": 3,
        "18": 4,
        "362": 4,
        "103": 4,
        "21": 5,
        "102": 5,
        "37": 6,
        "45": 6,
        "40": 7,
        "376": 7,
        "41": 8,
        "375": 8,
        "49": 9,
        "482": 9,
        "64": 10,
        "161": 10,
        "352": 10,
        "169": 10,
        "75": 10,
        "112": 10,
        "373": 10,
        "125": 10,
        "159": 10,
        "68": 11,
        "483": 11,
        "81": 12,
        "429": 12,
        "95": 12,
        "71": 12,
        "82": 13,
        "226": 13,
        "452": 14,
        "490": 14,
        "268": 14,
        "89": 14,
        "314": 14,
        "195": 15,
        "420": 15,
        "93": 15,
        "114": 16,
        "443": 16,
        "130": 17,
        "193": 17,
        "485": 17,
        "335": 17,
        "410": 17,
        "138": 18,
        "330": 18,
        "148": 19,
        "489": 19,
        "155": 20,
        "201": 20,
        "187": 21,
        "213": 21,
        "165": 21,
        "168": 22,
        "398": 22,
        "171": 23,
        "394": 23,
        "243": 23,
        "178": 24,
        "217": 24,
        "476": 24,
        "494": 24,
        "179": 25,
        "220": 25,
        "184": 26,
        "306": 26,
        "188": 27,
        "484": 27,
        "203": 28,
        "309": 28,
        "225": 29,
        "286": 29,
        "261": 30,
        "459": 30,
        "229": 30,
        "240": 31,
        "458": 31,
        "244": 32,
        "332": 32,
        "271": 33,
        "401": 33,
        "388": 34,
        "448": 34,
        "276": 34,
        "282": 35,
        "292": 35,
        "290": 36,
        "399": 36,
        "385": 37,
        "436": 37,
        "400": 38,
        "442": 38,
        "437": 38,
        "0": 39,
        "1": 40,
        "2": 41,
        "3": 42,
        "5": 43,
        "6": 44,
        "9": 45,
        "10": 46,
        "11": 47,
        "12": 48,
        "13": 49,
        "14": 50,
        "16": 51,
        "17": 52,
        "19": 53,
        "22": 54,
        "24": 55,
        "25": 56,
        "26": 57,
        "27": 58,
        "28": 59,
        "29": 60,
        "30": 61,
        "31": 62,
        "32": 63,
        "33": 64,
        "34": 65,
        "35": 66,
        "36": 67,
        "38": 68,
        "42": 69,
        "43": 70,
        "44": 71,
        "46": 72,
        "47": 73,
        "48": 74,
        "50": 75,
        "51": 76,
        "53": 77,
        "54": 78,
        "55": 79,
        "56": 80,
        "57": 81,
        "58": 82,
        "59": 83,
        "60": 84,
        "61": 85,
        "62": 86,
        "63": 87,
        "65": 88,
        "66": 89,
        "69": 90,
        "70": 91,
        "72": 92,
        "73": 93,
        "74": 94,
        "76": 95,
        "77": 96,
        "78": 97,
        "79": 98,
        "80": 99,
        "83": 100,
        "84": 101,
        "85": 102,
        "86": 103,
        "87": 104,
        "90": 105,
        "91": 106,
        "92": 107,
        "96": 108,
        "97": 109,
        "98": 110,
        "99": 111,
        "101": 112,
        "104": 113,
        "106": 114,
        "107": 115,
        "109": 116,
        "110": 117,
        "111": 118,
        "113": 119,
        "115": 120,
        "116": 121,
        "117": 122,
        "118": 123,
        "120": 124,
        "121": 125,
        "122": 126,
        "124": 127,
        "126": 128,
        "127": 129,
        "128": 130,
        "129": 131,
        "131": 132,
        "132": 133,
        "133": 134,
        "134": 135,
        "135": 136,
        "136": 137,
        "137": 138,
        "139": 139,
        "140": 140,
        "141": 141,
        "142": 142,
        "143": 143,
        "144": 144,
        "145": 145,
        "146": 146,
        "147": 147,
        "149": 148,
        "150": 149,
        "152": 150,
        "153": 151,
        "154": 152,
        "157": 153,
        "158": 154,
        "160": 155,
        "162": 156,
        "163": 157,
        "164": 158,
        "166": 159,
        "167": 160,
        "170": 161,
        "172": 162,
        "173": 163,
        "174": 164,
        "175": 165,
        "176": 166,
        "177": 167,
        "181": 168,
        "182": 169,
        "183": 170,
        "185": 171,
        "186": 172,
        "189": 173,
        "190": 174,
        "191": 175,
        "192": 176,
        "194": 177,
        "196": 178,
        "197": 179,
        "198": 180,
        "199": 181,
        "200": 182,
        "202": 183,
        "204": 184,
        "205": 185,
        "206": 186,
        "207": 187,
        "208": 188,
        "209": 189,
        "210": 190,
        "211": 191,
        "212": 192,
        "214": 193,
        "215": 194,
        "216": 195,
        "218": 196,
        "219": 197,
        "221": 198,
        "222": 199,
        "223": 200,
        "224": 201,
        "228": 202,
        "230": 203,
        "231": 204,
        "234": 205,
        "235": 206,
        "236": 207,
        "237": 208,
        "238": 209,
        "239": 210,
        "241": 211,
        "242": 212,
        "245": 213,
        "247": 214,
        "248": 215,
        "249": 216,
        "250": 217,
        "251": 218,
        "252": 219,
        "253": 220,
        "254": 221,
        "255": 222,
        "256": 223,
        "258": 224,
        "259": 225,
        "260": 226,
        "263": 227,
        "264": 228,
        "265": 229,
        "266": 230,
        "267": 231,
        "270": 232,
        "273": 233,
        "274": 234,
        "275": 235,
        "277": 236,
        "278": 237,
        "279": 238,
        "280": 239,
        "281": 240,
        "283": 241,
        "285": 242,
        "287": 243,
        "288": 244,
        "289": 245,
        "291": 246,
        "294": 247,
        "295": 248,
        "296": 249,
        "297": 250,
        "298": 251,
        "299": 252,
        "300": 253,
        "301": 254,
        "302": 255,
        "303": 256,
        "308": 257,
        "310": 258,
        "311": 259,
        "312": 260,
        "313": 261,
        "315": 262,
        "316": 263,
        "317": 264,
        "318": 265,
        "319": 266,
        "320": 267,
        "321": 268,
        "322": 269,
        "323": 270,
        "324": 271,
        "325": 272,
        "326": 273,
        "327": 274,
        "328": 275,
        "329": 276,
        "331": 277,
        "333": 278,
        "334": 279,
        "336": 280,
        "337": 281,
        "338": 282,
        "339": 283,
        "340": 284,
        "341": 285,
        "342": 286,
        "344": 287,
        "346": 288,
        "347": 289,
        "348": 290,
        "349": 291,
        "350": 292,
        "351": 293,
        "353": 294,
        "354": 295,
        "355": 296,
        "356": 297,
        "357": 298,
        "358": 299,
        "359": 300,
        "360": 301,
        "361": 302,
        "363": 303,
        "364": 304,
        "365": 305,
        "366": 306,
        "367": 307,
        "368": 308,
        "369": 309,
        "370": 310,
        "371": 311,
        "372": 312,
        "374": 313,
        "377": 314,
        "378": 315,
        "379": 316,
        "380": 317,
        "381": 318,
        "382": 319,
        "383": 320,
        "384": 321,
        "386": 322,
        "387": 323,
        "389": 324,
        "390": 325,
        "391": 326,
        "392": 327,
        "393": 328,
        "395": 329,
        "396": 330,
        "397": 331,
        "402": 332,
        "403": 333,
        "404": 334,
        "406": 335,
        "407": 336,
        "408": 337,
        "409": 338,
        "411": 339,
        "413": 340,
        "414": 341,
        "415": 342,
        "416": 343,
        "417": 344,
        "418": 345,
        "419": 346,
        "421": 347,
        "422": 348,
        "423": 349,
        "425": 350,
        "427": 351,
        "428": 352,
        "430": 353,
        "431": 354,
        "432": 355,
        "433": 356,
        "434": 357,
        "435": 358,
        "438": 359,
        "439": 360,
        "440": 361,
        "441": 362,
        "444": 363,
        "445": 364,
        "446": 365,
        "449": 366,
        "450": 367,
        "451": 368,
        "453": 369,
        "454": 370,
        "455": 371,
        "456": 372,
        "457": 373,
        "460": 374,
        "461": 375,
        "462": 376,
        "463": 377,
        "464": 378,
        "465": 379,
        "467": 380,
        "468": 381,
        "469": 382,
        "470": 383,
        "471": 384,
        "472": 385,
        "473": 386,
        "474": 387,
        "475": 388,
        "477": 389,
        "478": 390,
        "479": 391,
        "480": 392,
        "481": 393,
        "486": 394,
        "487": 395,
        "491": 396,
        "492": 397,
        "493": 398,
        "495": 399,
        "496": 400,
        "497": 401,
        "498": 402,
        "499": 403,
        "500": 404,
        "501": 405,
        "502": 406,
        "503": 407,
        "504": 408,
        "505": 409,
        "506": 410,
        "507": 411,
        "508": 412,
        "509": 413,
        "510": 414,
        "511": 415
    }
}